{"summaries":[{"symbol":{"__symbol":0,"members":[]},"metadata":{"__symbolic":"interface"}},{"symbol":{"__symbol":1,"members":[]},"metadata":{"__symbolic":"interface"}},{"symbol":{"__symbol":2,"members":[]},"metadata":{"__symbolic":"error","message":"Function call not supported","line":38,"character":28}},{"symbol":{"__symbol":3,"members":[]},"metadata":{"__symbolic":"call","expression":{"__symbol":2,"members":[]},"arguments":[20]}}],"symbols":[{"__symbol":0,"name":"Study","filePath":"/home/gabriel/devel/ng2-pack/src/app/table-example/people-mocks.d.ts"},{"__symbol":1,"name":"Person","filePath":"/home/gabriel/devel/ng2-pack/src/app/table-example/people-mocks.d.ts"},{"__symbol":2,"name":"generatePeople","filePath":"/home/gabriel/devel/ng2-pack/src/app/table-example/people-mocks.d.ts"},{"__symbol":3,"name":"people","filePath":"/home/gabriel/devel/ng2-pack/src/app/table-example/people-mocks.d.ts"}]}