{"summaries":[{"symbol":{"__symbol":0,"members":[]},"metadata":{"__symbolic":"interface"}},{"symbol":{"__symbol":1,"members":[]},"metadata":{"__symbolic":"interface"}},{"symbol":{"__symbol":2,"members":[]},"metadata":{"__symbolic":"interface"}},{"symbol":{"__symbol":3,"members":[]},"metadata":{"__symbolic":"interface"}},{"symbol":{"__symbol":4,"members":[]},"metadata":{"__symbolic":"interface"}},{"symbol":{"__symbol":5,"members":[]},"metadata":{"__symbolic":"interface"}}],"symbols":[{"__symbol":0,"name":"ColumnConfig","filePath":"/home/gabriel/devel/ng2-pack/src/lib/table/types.d.ts"},{"__symbol":1,"name":"SubFieldConfig","filePath":"/home/gabriel/devel/ng2-pack/src/lib/table/types.d.ts"},{"__symbol":2,"name":"ColumnLookup","filePath":"/home/gabriel/devel/ng2-pack/src/lib/table/types.d.ts"},{"__symbol":3,"name":"CompareFunctions","filePath":"/home/gabriel/devel/ng2-pack/src/lib/table/types.d.ts"},{"__symbol":4,"name":"DisplayFormatter","filePath":"/home/gabriel/devel/ng2-pack/src/lib/table/types.d.ts"},{"__symbol":5,"name":"Row","filePath":"/home/gabriel/devel/ng2-pack/src/lib/table/types.d.ts"}]}